<?xml version="1.0"?>
<products><product><productId>1</productId><name>Caviar Sleeve Knit</name><description>Cable knitted black base body, with contrasting pearl patterned sleeve detailing.</description><image>http://shop.fruitionlv.com/uploaded_images/KTZPatternedCrewneck.jpg</image><price>999</price></product><product><productId>2</productId><name>Denim Knitted Jacket</name><description> Dual paneled knitted jacket, with classic iconic denim front.</description><image>http://shop.fruitionlv.com/uploaded_images/DenimKnittedJacket1.jpg</image><price>1299</price></product><product><productId>3</productId><name>Norwegian Dark Knit </name><description>Timeworn norwegian dark diamond quatrefoil knit, with contrasting design. </description><image>http://shop.fruitionlv.com/uploaded_images/NorwegianDarkKnitFront.jpg</image><price>1799</price></product><product><productId>4</productId><name>Lumberjack Lodge Coat</name><description>Timeworn coat, with two chest welt pockets.</description><image>http://shop.fruitionlv.com/uploaded_images/PlaidLumbercoat.jpg</image><price>2499</price></product><product><productId>5</productId><name> Fair Isle Sweater</name><description>Timeworn fair isle double knitted sweater, with heather gray body.</description><image>http://shop.fruitionlv.com/uploaded_images/FairIsleDoubleKnit1.jpg</image><price>899</price></product><product><productId>6</productId><name>Norwegian Diamond Sweater</name><description>Timeworn norwegian diamond quatrefoil shawl sweater, with contrasting arm and lower body detailing.</description><image>http://shop.fruitionlv.com/uploaded_images/NorwegianKnittedShawl.jpg</image><price>1199</price></product><product><productId>7</productId><name>Aztec Summit Coat</name><description>Archival woolrich aztec summit coat, with red/green striped colorway.</description><image>http://shop.fruitionlv.com/uploaded_images/WoolrichAztecCoat.jpg</image><price>1299</price></product><product><productId>8</productId><name>Rustic Shawl Sweater</name><description>Cozy shawl collar, with single leather basket-woven button at the placket.</description><image>http://shop.fruitionlv.com/uploaded_images/Shawl-copy.jpg</image><price>799</price></product><product><productId>9</productId><name>Navajo Knit Vest</name><description>Archival Ralph Lauren polo navajo knit vest, with five-button front.</description><image>http://shop.fruitionlv.com/uploaded_images/rlknitvest1.jpg</image><price>999</price></product><product><productId>10</productId><name>Crystal Native Knit </name><description>Crystal serrated lightning native knit.</description><image>http://shop.fruitionlv.com/uploaded_images/sunburstps.jpg</image><price>1399</price></product><product><productId>11</productId><name>Polo Ski Knit</name><description>Timeworn norwegian ski knit, with contrasting design. </description><image>http://shop.fruitionlv.com/uploaded_images/ralphlaurenskips.jpg</image><price>899</price></product><product><productId>12</productId><name>Cookie Knit Sweater</name><description>Ralph Lauren cookie knit sweater.</description><image>http://shop.fruitionlv.com/uploaded_images/rlcookieknitps.jpg</image><price>699</price></product><product><productId>13</productId><name>Lightning Native Knit </name><description>Crystal serrated lightning native knit.</description><image>http://shop.fruitionlv.com/uploaded_images/sunburstps.jpg</image><price>1299</price></product><product><productId>14</productId><name>On Fire Cardigan</name><description>Phenomenon on fire cardigan, with ribbed V-neckline and placket.</description><image>http://shop.fruitionlv.com/uploaded_images/phenomenoncardigan.jpg</image><price>799</price></product><product><productId>15</productId><name>NauticalKnit</name><description>Nautical drawstring knit crewneck, with woven patched logo.</description><image>http://shop.fruitionlv.com/uploaded_images/Drawstring-Crewneck.jpg</image><price>899</price></product></products>
